<?xml version='1.0' encoding='utf_8'?>
<sprites>
    <i name="別顔_照れ_59" src="剧本自定义附件/Little Devil Plus/Face_59_L.webp" param="810,0,270,270" />
    <i name="別顔_吐息_59" src="剧本自定义附件/Little Devil Plus/Face_59_L.webp" param="540,540,270,270" />
    <i name="別顔_汗_59" src="剧本自定义附件/Little Devil Plus/Face_59_L.webp" param="810,540,270,270" />
    <i name="特別拡張_59" src="剧本自定义附件/Little Devil Plus/Face_59_L.webp" param="0,0,270,270" />
    <i name="別顔_服_通常_59" src="剧本自定义附件/Little Devil Plus/Face_59_L.webp" param="0,0,270,270" />
    <i name="別顔_服_笑顔_59" src="剧本自定义附件/Little Devil Plus/Face_59_L.webp" param="270,0,270,270" />
    <i name="別顔_服_憤怒_59" src="剧本自定义附件/Little Devil Plus/Face_59_L.webp" param="540,0,270,270" />
    <i name="別顔_服_発情_59" src="剧本自定义附件/Little Devil Plus/Face_59_L.webp" param="1350,0,270,270" />
    <i name="別顔_服_Ｍ_通常_59" src="剧本自定义附件/Little Devil Plus/Face_59_M.webp" param="0,0,270,270" />
    <i name="別顔_服_Ｍ_笑顔_59" src="剧本自定义附件/Little Devil Plus/Face_59_M.webp" param="270,0,270,270" />
    <i name="別顔_服_Ｍ_憤怒_59" src="剧本自定义附件/Little Devil Plus/Face_59_M.webp" param="540,0,270,270" />
    <i name="別顔_服_Ｍ_発情_59" src="剧本自定义附件/Little Devil Plus/Face_59_M.webp" param="1350,0,270,270" />
    <i name="別顔_服_Ｓ_通常_59" src="剧本自定义附件/Little Devil Plus/Face_59_S.webp" param="0,0,270,270" />
    <i name="別顔_服_Ｓ_笑顔_59" src="剧本自定义附件/Little Devil Plus/Face_59_S.webp" param="270,0,270,270" />
    <i name="別顔_服_Ｓ_憤怒_59" src="剧本自定义附件/Little Devil Plus/Face_59_S.webp" param="540,0,270,270" />
    <i name="別顔_服_Ｓ_発情_59" src="剧本自定义附件/Little Devil Plus/Face_59_S.webp" param="1350,0,270,270" />
    <i name="別顔_裸_通常_59" src="剧本自定义附件/Little Devil Plus/Face_59_L.webp" param="0,270,270,270" />
    <i name="別顔_裸_笑顔_59" src="剧本自定义附件/Little Devil Plus/Face_59_L.webp" param="270,270,270,270" />
    <i name="別顔_裸_憤怒_59" src="剧本自定义附件/Little Devil Plus/Face_59_L.webp" param="540,270,270,270" />
    <i name="別顔_裸_発情_59" src="剧本自定义附件/Little Devil Plus/Face_59_L.webp" param="1350,270,270,270" />
    <i name="別顔_裸_自慰_59" src="剧本自定义附件/Little Devil Plus/Face_59_L.webp" param="1080,270,270,270" />
    <i name="別顔_裸_愛撫_59" src="剧本自定义附件/Little Devil Plus/Face_59_L.webp" param="0,540,270,270" />
    <i name="別顔_裸_性交_59" src="剧本自定义附件/Little Devil Plus/Face_59_L.webp" param="270,540,270,270" />
    <i name="別顔_裸_Ｍ_通常_59" src="剧本自定义附件/Little Devil Plus/Face_59_M.webp" param="0,270,270,270" />
    <i name="別顔_裸_Ｍ_笑顔_59" src="剧本自定义附件/Little Devil Plus/Face_59_M.webp" param="270,270,270,270" />
    <i name="別顔_裸_Ｍ_憤怒_59" src="剧本自定义附件/Little Devil Plus/Face_59_M.webp" param="540,270,270,270" />
    <i name="別顔_裸_Ｍ_発情_59" src="剧本自定义附件/Little Devil Plus/Face_59_M.webp" param="1350,270,270,270" />
    <i name="別顔_裸_Ｍ_自慰_59" src="剧本自定义附件/Little Devil Plus/Face_59_M.webp" param="1080,270,270,270" />
    <i name="別顔_裸_Ｍ_愛撫_59" src="剧本自定义附件/Little Devil Plus/Face_59_M.webp" param="0,540,270,270" />
    <i name="別顔_裸_Ｍ_性交_59" src="剧本自定义附件/Little Devil Plus/Face_59_M.webp" param="270,540,270,270" />
    <i name="別顔_裸_Ｓ_通常_59" src="剧本自定义附件/Little Devil Plus/Face_59_S.webp" param="0,270,270,270" />
    <i name="別顔_裸_Ｓ_笑顔_59" src="剧本自定义附件/Little Devil Plus/Face_59_S.webp" param="270,270,270,270" />
    <i name="別顔_裸_Ｓ_憤怒_59" src="剧本自定义附件/Little Devil Plus/Face_59_S.webp" param="540,270,270,270" />
    <i name="別顔_裸_Ｓ_発情_59" src="剧本自定义附件/Little Devil Plus/Face_59_S.webp" param="1350,270,270,270" />
    <i name="別顔_裸_Ｓ_自慰_59" src="剧本自定义附件/Little Devil Plus/Face_59_S.webp" param="1080,270,270,270" />
    <i name="別顔_裸_Ｓ_愛撫_59" src="剧本自定义附件/Little Devil Plus/Face_59_S.webp" param="0,540,270,270" />
    <i name="別顔_裸_Ｓ_性交_59" src="剧本自定义附件/Little Devil Plus/Face_59_S.webp" param="270,540,270,270" />
    <i name="別立ち_服_通常_59" src="剧本自定义附件/Little Devil Plus/Stand_59_L.webp" param="0,0,270,270" />
    <i name="別立ち_服_笑顔_59" src="剧本自定义附件/Little Devil Plus/Stand_59_L.webp" param="270,0,270,270" />
    <i name="別立ち_服_憤怒_59" src="剧本自定义附件/Little Devil Plus/Stand_59_L.webp" param="540,0,270,270" />
    <i name="別立ち_服_Ｍ_通常_59" src="剧本自定义附件/Little Devil Plus/Stand_59_M.webp" param="0,0,270,270" />
    <i name="別立ち_服_Ｍ_笑顔_59" src="剧本自定义附件/Little Devil Plus/Stand_59_M.webp" param="270,0,270,270" />
    <i name="別立ち_服_Ｍ_憤怒_59" src="剧本自定义附件/Little Devil Plus/Stand_59_M.webp" param="540,0,270,270" />
    <i name="別立ち_服_Ｓ_通常_59" src="剧本自定义附件/Little Devil Plus/Stand_59_S.webp" param="0,0,270,270" />
    <i name="別立ち_服_Ｓ_笑顔_59" src="剧本自定义附件/Little Devil Plus/Stand_59_S.webp" param="270,0,270,270" />
    <i name="別立ち_服_Ｓ_憤怒_59" src="剧本自定义附件/Little Devil Plus/Stand_59_S.webp" param="540,0,270,270" />
    <i name="別立ち_裸_通常_59" src="剧本自定义附件/Little Devil Plus/Stand_59_L.webp" param="0,270,270,270" />
    <i name="別立ち_裸_笑顔_59" src="剧本自定义附件/Little Devil Plus/Stand_59_L.webp" param="270,270,270,270" />
    <i name="別立ち_裸_憤怒_59" src="剧本自定义附件/Little Devil Plus/Stand_59_L.webp" param="540,270,270,270" />
    <i name="別立ち_裸_Ｍ_通常_59" src="剧本自定义附件/Little Devil Plus/Stand_59_M.webp" param="0,270,270,270" />
    <i name="別立ち_裸_Ｍ_笑顔_59" src="剧本自定义附件/Little Devil Plus/Stand_59_M.webp" param="270,270,270,270" />
    <i name="別立ち_裸_Ｍ_憤怒_59" src="剧本自定义附件/Little Devil Plus/Stand_59_M.webp" param="540,270,270,270" />
    <i name="別立ち_裸_Ｓ_通常_59" src="剧本自定义附件/Little Devil Plus/Stand_59_S.webp" param="0,270,270,270" />
    <i name="別立ち_裸_Ｓ_笑顔_59" src="剧本自定义附件/Little Devil Plus/Stand_59_S.webp" param="270,270,270,270" />
    <i name="別立ち_裸_Ｓ_憤怒_59" src="剧本自定义附件/Little Devil Plus/Stand_59_S.webp" param="540,270,270,270" />
    <i name="別顔_妊娠服_通常_59" src="剧本自定义附件/Little Devil Plus/Face_59_L_P.webp" param="0,0,270,270" />
    <i name="別顔_妊娠服_笑顔_59" src="剧本自定义附件/Little Devil Plus/Face_59_L_P.webp" param="270,0,270,270" />
    <i name="別顔_妊娠服_憤怒_59" src="剧本自定义附件/Little Devil Plus/Face_59_L_P.webp" param="540,0,270,270" />
    <i name="別顔_妊娠服_発情_59" src="剧本自定义附件/Little Devil Plus/Face_59_L_P.webp" param="1350,0,270,270" />
    <i name="別顔_妊娠服_Ｍ_通常_59" src="剧本自定义附件/Little Devil Plus/Face_59_M_P.webp" param="0,0,270,270" />
    <i name="別顔_妊娠服_Ｍ_笑顔_59" src="剧本自定义附件/Little Devil Plus/Face_59_M_P.webp" param="270,0,270,270" />
    <i name="別顔_妊娠服_Ｍ_憤怒_59" src="剧本自定义附件/Little Devil Plus/Face_59_M_P.webp" param="540,0,270,270" />
    <i name="別顔_妊娠服_Ｍ_発情_59" src="剧本自定义附件/Little Devil Plus/Face_59_M_P.webp" param="1350,0,270,270" />
    <i name="別顔_妊娠服_Ｓ_通常_59" src="剧本自定义附件/Little Devil Plus/Face_59_S_P.webp" param="0,0,270,270" />
    <i name="別顔_妊娠服_Ｓ_笑顔_59" src="剧本自定义附件/Little Devil Plus/Face_59_S_P.webp" param="270,0,270,270" />
    <i name="別顔_妊娠服_Ｓ_憤怒_59" src="剧本自定义附件/Little Devil Plus/Face_59_S_P.webp" param="540,0,270,270" />
    <i name="別顔_妊娠服_Ｓ_発情_59" src="剧本自定义附件/Little Devil Plus/Face_59_S_P.webp" param="1350,0,270,270" />
    <i name="別顔_妊娠裸_通常_59" src="剧本自定义附件/Little Devil Plus/Face_59_L_P.webp" param="0,270,270,270" />
    <i name="別顔_妊娠裸_笑顔_59" src="剧本自定义附件/Little Devil Plus/Face_59_L_P.webp" param="270,270,270,270" />
    <i name="別顔_妊娠裸_憤怒_59" src="剧本自定义附件/Little Devil Plus/Face_59_L_P.webp" param="540,270,270,270" />
    <i name="別顔_妊娠裸_発情_59" src="剧本自定义附件/Little Devil Plus/Face_59_L_P.webp" param="1350,270,270,270" />
    <i name="別顔_妊娠裸_自慰_59" src="剧本自定义附件/Little Devil Plus/Face_59_L_P.webp" param="1080,270,270,270" />
    <i name="別顔_妊娠裸_愛撫_59" src="剧本自定义附件/Little Devil Plus/Face_59_L_P.webp" param="0,540,270,270" />
    <i name="別顔_妊娠裸_性交_59" src="剧本自定义附件/Little Devil Plus/Face_59_L_P.webp" param="270,540,270,270" />
    <i name="別顔_妊娠裸_Ｍ_通常_59" src="剧本自定义附件/Little Devil Plus/Face_59_M_P.webp" param="0,270,270,270" />
    <i name="別顔_妊娠裸_Ｍ_笑顔_59" src="剧本自定义附件/Little Devil Plus/Face_59_M_P.webp" param="270,270,270,270" />
    <i name="別顔_妊娠裸_Ｍ_憤怒_59" src="剧本自定义附件/Little Devil Plus/Face_59_M_P.webp" param="540,270,270,270" />
    <i name="別顔_妊娠裸_Ｍ_発情_59" src="剧本自定义附件/Little Devil Plus/Face_59_M_P.webp" param="1350,270,270,270" />
    <i name="別顔_妊娠裸_Ｍ_自慰_59" src="剧本自定义附件/Little Devil Plus/Face_59_M_P.webp" param="1080,270,270,270" />
    <i name="別顔_妊娠裸_Ｍ_愛撫_59" src="剧本自定义附件/Little Devil Plus/Face_59_M_P.webp" param="0,540,270,270" />
    <i name="別顔_妊娠裸_Ｍ_性交_59" src="剧本自定义附件/Little Devil Plus/Face_59_M_P.webp" param="270,540,270,270" />
    <i name="別顔_妊娠裸_Ｓ_通常_59" src="剧本自定义附件/Little Devil Plus/Face_59_S_P.webp" param="0,270,270,270" />
    <i name="別顔_妊娠裸_Ｓ_笑顔_59" src="剧本自定义附件/Little Devil Plus/Face_59_S_P.webp" param="270,270,270,270" />
    <i name="別顔_妊娠裸_Ｓ_憤怒_59" src="剧本自定义附件/Little Devil Plus/Face_59_S_P.webp" param="540,270,270,270" />
    <i name="別顔_妊娠裸_Ｓ_発情_59" src="剧本自定义附件/Little Devil Plus/Face_59_S_P.webp" param="1350,270,270,270" />
    <i name="別顔_妊娠裸_Ｓ_自慰_59" src="剧本自定义附件/Little Devil Plus/Face_59_S_P.webp" param="1080,270,270,270" />
    <i name="別顔_妊娠裸_Ｓ_愛撫_59" src="剧本自定义附件/Little Devil Plus/Face_59_S_P.webp" param="0,540,270,270" />
    <i name="別顔_妊娠裸_Ｓ_性交_59" src="剧本自定义附件/Little Devil Plus/Face_59_S_P.webp" param="270,540,270,270" />
    <i name="別立ち_妊娠服_通常_59" src="剧本自定义附件/Little Devil Plus/Stand_59_L_P.webp" param="0,0,270,270" />
    <i name="別立ち_妊娠服_笑顔_59" src="剧本自定义附件/Little Devil Plus/Stand_59_L_P.webp" param="270,0,270,270" />
    <i name="別立ち_妊娠服_憤怒_59" src="剧本自定义附件/Little Devil Plus/Stand_59_L_P.webp" param="540,0,270,270" />
    <i name="別立ち_妊娠服_Ｍ_通常_59" src="剧本自定义附件/Little Devil Plus/Stand_59_M_P.webp" param="0,0,270,270" />
    <i name="別立ち_妊娠服_Ｍ_笑顔_59" src="剧本自定义附件/Little Devil Plus/Stand_59_M_P.webp" param="270,0,270,270" />
    <i name="別立ち_妊娠服_Ｍ_憤怒_59" src="剧本自定义附件/Little Devil Plus/Stand_59_M_P.webp" param="540,0,270,270" />
    <i name="別立ち_妊娠服_Ｓ_通常_59" src="剧本自定义附件/Little Devil Plus/Stand_59_S_P.webp" param="0,0,270,270" />
    <i name="別立ち_妊娠服_Ｓ_笑顔_59" src="剧本自定义附件/Little Devil Plus/Stand_59_S_P.webp" param="270,0,270,270" />
    <i name="別立ち_妊娠服_Ｓ_憤怒_59" src="剧本自定义附件/Little Devil Plus/Stand_59_S_P.webp" param="540,0,270,270" />
    <i name="別立ち_妊娠裸_通常_59" src="剧本自定义附件/Little Devil Plus/Stand_59_L_P.webp" param="0,270,270,270" />
    <i name="別立ち_妊娠裸_笑顔_59" src="剧本自定义附件/Little Devil Plus/Stand_59_L_P.webp" param="270,270,270,270" />
    <i name="別立ち_妊娠裸_憤怒_59" src="剧本自定义附件/Little Devil Plus/Stand_59_L_P.webp" param="540,270,270,270" />
    <i name="別立ち_妊娠裸_Ｍ_通常_59" src="剧本自定义附件/Little Devil Plus/Stand_59_M_P.webp" param="0,270,270,270" />
    <i name="別立ち_妊娠裸_Ｍ_笑顔_59" src="剧本自定义附件/Little Devil Plus/Stand_59_M_P.webp" param="270,270,270,270" />
    <i name="別立ち_妊娠裸_Ｍ_憤怒_59" src="剧本自定义附件/Little Devil Plus/Stand_59_M_P.webp" param="540,270,270,270" />
    <i name="別立ち_妊娠裸_Ｓ_通常_59" src="剧本自定义附件/Little Devil Plus/Stand_59_S_P.webp" param="0,270,270,270" />
    <i name="別立ち_妊娠裸_Ｓ_笑顔_59" src="剧本自定义附件/Little Devil Plus/Stand_59_S_P.webp" param="270,270,270,270" />
    <i name="別立ち_妊娠裸_Ｓ_憤怒_59" src="剧本自定义附件/Little Devil Plus/Stand_59_S_P.webp" param="540,270,270,270" />
</sprites>